lso/__init__.py
lso/app.py
lso/config.py
lso/environment.py
lso/execute.py
lso/playbook.py
lso/routes/__init__.py
lso/routes/default.py
lso/routes/execute.py
lso/routes/playbook.py
lso/schema.py
lso/tasks.py
lso/utils.py
lso/worker.py
orchestrator_lso-2.4.3.dist-info/WHEEL
orchestrator_lso-2.4.3.dist-info/METADATA
orchestrator_lso-2.4.3.dist-info/RECORD
