Metadata-Version: 2.4
Name: orchestrator-lso
Version: 2.4.3
Summary: LSO, an API for remotely running Ansible playbooks.
Author: GÉANT Orchestration and Automation Team
Author-email: GÉANT Orchestration and Automation Team <goat@geant.org>
License-Expression: Apache-2.0
Classifier: Intended Audience :: Information Technology
Classifier: Intended Audience :: System Administrators
Classifier: Operating System :: OS Independent
Classifier: Programming Language :: Python :: 3
Classifier: Programming Language :: Python
Classifier: Topic :: Internet
Classifier: Topic :: Software Development :: Libraries :: Application Frameworks
Classifier: Topic :: Software Development :: Libraries :: Python Modules
Classifier: Topic :: Software Development :: Libraries
Classifier: Topic :: Software Development
Classifier: Typing :: Typed
Classifier: Development Status :: 5 - Production/Stable
Classifier: Environment :: Web Environment
Classifier: Framework :: FastAPI
Classifier: Intended Audience :: Developers
Classifier: Intended Audience :: Telecommunications Industry
Classifier: Programming Language :: Python :: 3 :: Only
Classifier: Programming Language :: Python :: 3.11
Classifier: Programming Language :: Python :: 3.12
Requires-Dist: ansible-runner==2.4.2
Requires-Dist: ansible==10.7.0
Requires-Dist: fastapi==0.121.1
Requires-Dist: httpx==0.28.1
Requires-Dist: uvicorn[standard]==0.38.0
Requires-Dist: requests==2.32.5
Requires-Dist: pydantic-settings==2.11.0
Requires-Dist: celery==5.5.3
Requires-Dist: redis==5.3.1
Requires-Python: >=3.11, <3.14
Project-URL: Documentation, https://docs.gap.geant.org
Project-URL: Homepage, https://workfloworchestrator.org/lso/
Project-URL: Source, https://github.com/workfloworchestrator/lso
